country_converter/__init__.py
country_converter/country_converter.py
country_converter/country_data.tsv
country_converter/version.py
country_converter-1.3.1.dist-info/licenses/LICENSE
country_converter-1.3.1.dist-info/METADATA
country_converter-1.3.1.dist-info/WHEEL
country_converter-1.3.1.dist-info/entry_points.txt
country_converter-1.3.1.dist-info/top_level.txt
country_converter-1.3.1.dist-info/RECORD
