Metadata-Version: 2.4
Name: country_converter
Version: 1.3.1
Summary: The country converter (coco) - a Python package for converting country names between different classifications schemes
Author-email: Konstantin Stadler <konstantin.stadler@ntnu.no>
License: GNU General Public License v3 (GPLv3)
Project-URL: Repository, https://github.com/IndEcol/country_converter
Keywords: country,ISO 3166
Classifier: Development Status :: 4 - Beta
Classifier: Environment :: Console
Classifier: Intended Audience :: End Users/Desktop
Classifier: Intended Audience :: Developers
Classifier: Intended Audience :: Science/Research
Classifier: License :: OSI Approved :: GNU General Public License v3 (GPLv3)
Classifier: Operating System :: OS Independent
Classifier: Programming Language :: Python
Classifier: Programming Language :: Python :: 3 :: Only
Classifier: Programming Language :: Python :: 3.9
Classifier: Programming Language :: Python :: 3.10
Classifier: Programming Language :: Python :: 3.11
Classifier: Programming Language :: Python :: 3.12
Classifier: Programming Language :: Python :: 3.13
Classifier: Topic :: Scientific/Engineering
Classifier: Topic :: Utilities
Requires-Python: >=3.9
License-File: LICENSE
Requires-Dist: pandas>=1.0
Provides-Extra: dev
Requires-Dist: pdbpp; extra == "dev"
Requires-Dist: ipython; extra == "dev"
Requires-Dist: jupyterlab==3.*; extra == "dev"
Requires-Dist: jupytext; extra == "dev"
Requires-Dist: pynvim; extra == "dev"
Requires-Dist: ipykernel; extra == "dev"
Requires-Dist: poethepoet; extra == "dev"
Provides-Extra: test
Requires-Dist: coveralls; extra == "test"
Requires-Dist: pytest>=5.4.0; extra == "test"
Requires-Dist: pytest-cov>=2.7.0; extra == "test"
Requires-Dist: pytest-datadir; extra == "test"
Requires-Dist: pytest-mypy; extra == "test"
Requires-Dist: pytest-ruff>=0.5; extra == "test"
Requires-Dist: pytest-xdist[psutil]; extra == "test"
Dynamic: license-file
